{
  "name": "Image",
  "id": "image",
  "icon": "fad fa-image-polaroid",
  "category": "media",
  "fields": [
    {
      "name": "Image",
      "id": "image",
      "type": "upload_single",
      "default": "https://images.unsplash.com/photo-1554995207-c18c203602cb?ixid=MXwxMjA3fDB8MHxwaG90by1wYWdlfHx8fGVufDB8fHw%3D&ixlib=rb-1.2.1&auto=format&fit=crop&w=2850&q=80"
    },
    {
      "name": "Border radius",
      "id": "border_radius",
      "type": "select",
      "default": "",
      "sync": true,
      "options": {
        "": "None",
        "rounded": "Small",
        "rounded-lg": "Large",
        "rounded-xl": "XL",
        "rounded-full": "Full"
      }
    },
    {
      "name": "Aspect ratio",
      "id": "aspect_ratio",
      "type": "select",
      "default": "4/3",
      "sync": true,
      "options": {
        "square": "Square",
        "4/3": "Photo",
        "5/6": "Vertical (regular)",
        "2/3": "Vertical (tall)",
        "16/9": "Horizontal (widescreen)",
        "21/9": "Horizontal (cinema)"
      }
    }
  ]
}
